suricata/__init__.py
suricata/update/__init__.py
suricata/update/config.py
suricata/update/engine.py
suricata/update/exceptions.py
suricata/update/extract.py
suricata/update/loghandler.py
suricata/update/main.py
suricata/update/maps.py
suricata/update/matchers.py
suricata/update/net.py
suricata/update/notes.py
suricata/update/osinfo.py
suricata/update/parsers.py
suricata/update/revision.py
suricata/update/rule.py
suricata/update/sources.py
suricata/update/util.py
suricata/update/version.py
suricata/update/commands/__init__.py
suricata/update/commands/addsource.py
suricata/update/commands/checkversions.py
suricata/update/commands/disablesource.py
suricata/update/commands/enablesource.py
suricata/update/commands/listsources.py
suricata/update/commands/removesource.py
suricata/update/commands/updatesources.py
suricata/update/compat/__init__.py
suricata/update/compat/ordereddict.py
suricata/update/compat/argparse/__init__.py
suricata/update/compat/argparse/argparse.py
suricata/update/configs/__init__.py
suricata/update/configs/disable.conf
suricata/update/configs/drop.conf
suricata/update/configs/enable.conf
suricata/update/configs/modify.conf
suricata/update/configs/threshold.in
suricata/update/configs/update.yaml
suricata/update/data/__init__.py
suricata/update/data/index.py
suricata/update/data/update.py
suricata_update-1.2.1.data/scripts/suricata-update
suricata_update-1.2.1.dist-info/LICENSE
suricata_update-1.2.1.dist-info/METADATA
suricata_update-1.2.1.dist-info/WHEEL
suricata_update-1.2.1.dist-info/top_level.txt
suricata_update-1.2.1.dist-info/RECORD
