Metadata-Version: 2.1
Name: suricata-update
Version: 1.2.1
Summary: Suricata Update Tool
Home-page: https://github.com/OISF/suricata-update
Author: Jason Ish
Author-email: ish@unx.ca
License: GPLv2
Platform: UNKNOWN
Classifier: License :: OSI Approved :: GNU General Public License v2 (GPLv2)
